{
  "_class": "shapePath",
  "booleanOperation": -1,
  "do_objectID": "3F67731A-711A-43AB-9D35-709DB4531397",
  "edited": true,
  "exportOptions": {
    "_class": "exportOptions",
    "do_objectID": "93CA6450-64F8-4CA2-B049-CA2224C25FCE",
    "exportFormats": [
    ],
    "includedLayerIds": [
    ],
    "layerOptions": 0,
    "shouldTrim": false
  },
  "frame": {
    "_class": "rect",
    "constrainProportions": false,
    "do_objectID": "897CDA58-87F6-4ED3-8BE7-0972B6AAB4BD",
    "height": 24.18798845779928,
    "width": 24.18798845779923,
    "x": 0,
    "y": 0
  },
  "isClosed": false,
  "isFlippedHorizontal": false,
  "isFlippedVertical": false,
  "isLocked": false,
  "isVisible": true,
  "layerListExpandedType": 0,
  "name": "Path",
  "nameIsFixed": false,
  "pointRadiusBehaviour": 1,
  "points": [
    {
      "_class": "curvePoint",
      "cornerRadius": 0,
      "curveFrom": "{0.22385642640231029, 0}",
      "curveMode": 4,
      "curveTo": "{0.50000000000000011, 0}",
      "hasCurveFrom": true,
      "hasCurveTo": false,
      "point": "{0.50000000000000011, 0}"
    },
    {
      "_class": "curvePoint",
      "cornerRadius": 0,
      "curveFrom": "{0, 0.59300692978210812}",
      "curveMode": 3,
      "curveTo": "{0, 0.22385908556658807}",
      "hasCurveFrom": true,
      "hasCurveTo": true,
      "point": "{0, 0.5}"
    },
    {
      "_class": "curvePoint",
      "cornerRadius": 0,
      "curveFrom": "{0.046189683506267669, 0.71008195544304331}",
      "curveMode": 4,
      "curveTo": "{0.001957144908498131, 0.6354923974493295}",
      "hasCurveFrom": false,
      "hasCurveTo": true,
      "point": "{0.046189683506267669, 0.71008195544304331}"
    },
    {
      "_class": "curvePoint",
      "cornerRadius": 0,
      "curveFrom": "{0, 1}",
      "curveMode": 1,
      "curveTo": "{0, 1}",
      "hasCurveFrom": false,
      "hasCurveTo": false,
      "point": "{0, 1}"
    },
    {
      "_class": "curvePoint",
      "cornerRadius": 0,
      "curveFrom": "{0.3451807965792511, 0.98648346797568465}",
      "curveMode": 4,
      "curveTo": "{0.27254040600120194, 0.94534353743305566}",
      "hasCurveFrom": true,
      "hasCurveTo": false,
      "point": "{0.27254040600120194, 0.94534353743305566}"
    },
    {
      "_class": "curvePoint",
      "cornerRadius": 0,
      "curveFrom": "{0.77614357359768982, 1}",
      "curveMode": 3,
      "curveTo": "{0.41055635035021193, 1}",
      "hasCurveFrom": true,
      "hasCurveTo": true,
      "point": "{0.50000000000000011, 1}"
    },
    {
      "_class": "curvePoint",
      "cornerRadius": 0,
      "curveFrom": "{1, 0.22385908556658807}",
      "curveMode": 2,
      "curveTo": "{1, 0.77614357359768971}",
      "hasCurveFrom": true,
      "hasCurveTo": true,
      "point": "{1, 0.5}"
    },
    {
      "_class": "curvePoint",
      "cornerRadius": 0,
      "curveFrom": "{0.50000000000000011, 0}",
      "curveMode": 4,
      "curveTo": "{0.77614357359768982, 0}",
      "hasCurveFrom": false,
      "hasCurveTo": true,
      "point": "{0.50000000000000011, 0}"
    }
  ],
  "resizingConstraint": 63,
  "resizingType": 0,
  "rotation": 0,
  "shouldBreakMaskChain": false
}